setup.py
moc/__init__.py
moc/event.py
moc.egg-info/PKG-INFO
moc.egg-info/SOURCES.txt
moc.egg-info/dependency_links.txt
moc.egg-info/top_level.txt