Metadata-Version: 1.0
Name: moc
Version: 0.2
Summary: Music On Console Python interface
Home-page: http://moc.lophus.org
Author: Jonas Haag
Author-email: jonas@lophus.org
License: BSD
Platform: UNKNOWN
